<?xml version="1.0"?>
<!-- $Id$ -->
<!--
  Vinson -set file for FlightGear.

  Copyright (C) 2007 - 2009  Anders Gidenstam  (anders(at)gidenstam.org)
  This file is released under the GPL license version 2 or later.
-->
<PropertyList include="common.xml">

	<sim include="Systems/nimitz-views.xml">

		<description>Multiplayer carrier Carl Vinson - Other pilots can land on it.</description>
		<author>Anders Gidenstam, Vivian Meazza</author>
		<status>alpha</status>
		<aircraft-version>0.1</aircraft-version>

		<flight-model>null</flight-model>

		<presets>
			<onground>true</onground>
		</presets>

		<startup>
			<splash-texture>Aircraft/MPCarrier/nimitz-splash.rgb</splash-texture>
		</startup>

		<sound>
			<audible>false</audible>
			<path/>
		</sound>

		<model>
			<path>Aircraft/MPCarrier/Models/mp-vinson.xml</path>
		</model>

		<systems>

			<electrical>

			</electrical>

			<static>
			</static>

		</systems>

		<!--<panel>
			<path>Aircraft/MPCarrier/Panels/MP-ATC-panel2.xml</path>
			<visibility>false</visibility>
		</panel>

		<instrumentation>
			<path>Aircraft/ATC/instrumentation.xml</path>
		</instrumentation>-->


		<!-- This aircraft is pointless without the vinson_demo scenario. -->
		<ai>
			<enabled type="bool">true</enabled>
			<scenario n="100">vinson_demo</scenario>
		</ai>

		<mp-carriers>
			<vinson-callsign type="string"></vinson-callsign>
		</mp-carriers>

		<multiplay>
			<chat_display>1</chat_display>
		</multiplay>

		<atc>
			<target-id type="string"></target-id>
			<target-alt type="double">0</target-alt>
			<target-number type="int">-1</target-number>
			<target-range type="double">0</target-range>
		</atc>

	</sim>

	<controls>
		<rudder-pos-deg type="float"> 0.0 </rudder-pos-deg>
		<speed-kts type="float"> 0.0 </speed-kts>
	</controls>

	<surface-positions>
		<!-- These will be (ab)used for transmitting rudder-deg and speed-kts. -->
		<rudder-pos-norm type="float"> 0.0 </rudder-pos-norm>
		<flap-pos-norm type="float"> 0.0 </flap-pos-norm>
	</surface-positions>

	<instrumentation>
		<radar>
			<switch type="string">ON</switch>
			<mode-control type="int">1</mode-control>
			<display-controls>
				<WX type="bool">false</WX>
				<pos type="bool">true</pos>
				<data type="bool">true</data>
				<symbol type="bool">true</symbol>
				<rotate type="bool">false</rotate>
			</display-controls>
			<serviceable type="bool">true</serviceable>
			<range type="int">8</range>
			<mode type="string">WX</mode>
			<lightning type="bool">true</lightning>
			<display-mode type="string">plan</display-mode>
			<!--<echo-texture-path type="string"
												 archive="y">Aircraft/ATC/Ver2/atcecho.png</echo-texture-path>-->
			<minimized type="bool">false</minimized>
			<heading-marker type="bool">false</heading-marker>
			<reference-range-nm type="double">100</reference-range-nm>
			<limit-deg type="int">180</limit-deg>
			<font>
				<name type="string">typewriter.txf</name>
				<size type="float">5</size>
				<line-spacing type="float">0.25</line-spacing>
				<color>
					<red type="float">0</red>
					<green type="float">0.8</green>
					<blue type="float">0</blue>
					<alpha type="float">1</alpha>
				</color>
			</font>
		</radar>
	</instrumentation>

	<nasal>
		<!-- Nasal Carrier View -->
		<CarrierControl>
			<file>Aircraft/MPCarrier/Systems/commander.nas</file>
			<script>
				var carrier_name = "Vinson";
			</script>
		</CarrierControl>
		<approachview>
			<file>Aircraft/MPCarrier/Systems/approachview.nas</file>
		</approachview>
		<lsoview>
			<file>Aircraft/MPCarrier/Systems/lsoview.nas</file>
		</lsoview>
		<!--<ATC>
			<file>Aircraft/MPCarrier/Panels/atc2.nas</file>
		</ATC>-->
	</nasal>

</PropertyList>
